m3uclean/__init__.py
m3uclean/app.py
m3uclean/cleaner.py
m3uclean/parser.py
m3uclean/validator.py
m3uclean/writer.py
m3uclean-1.0.0.dist-info/LICENSE
m3uclean-1.0.0.dist-info/METADATA
m3uclean-1.0.0.dist-info/WHEEL
m3uclean-1.0.0.dist-info/entry_points.txt
m3uclean-1.0.0.dist-info/top_level.txt
m3uclean-1.0.0.dist-info/RECORD
