Metadata-Version: 2.2
Name: M3UClean
Version: 1.0.0
Summary: A tool for validating and cleaning M3U playlists
Home-page: https://github.com/samestrin/m3uclean
Author: Sam Estrin
Classifier: Programming Language :: Python :: 3
Classifier: License :: OSI Approved :: MIT License
Classifier: Operating System :: OS Independent
Requires-Python: >=3.7
License-File: LICENSE
Requires-Dist: certifi==2025.1.31
Requires-Dist: charset-normalizer==3.4.1
Requires-Dist: idna==3.10
Requires-Dist: requests==2.32.3
Requires-Dist: tenacity==9.0.0
Requires-Dist: urllib3==2.3.0
Dynamic: author
Dynamic: classifier
Dynamic: description
Dynamic: description-content-type
Dynamic: home-page
Dynamic: requires-dist
Dynamic: requires-python
Dynamic: summary
